Metadata-Version: 2.1
Name: batman-curve
Version: 1.0
Summary: A Python library for generating the iconic Batman curve.
Home-page: https://github.com/avitase/batman-curve
Author: Nis Meinert
Author-email: mail@nismeinert.de
Requires-Python: >=3.10
License-File: LICENSE
Requires-Dist: numpy
Provides-Extra: dev
Requires-Dist: pre-commit; extra == "dev"
Requires-Dist: pytest; extra == "dev"
Requires-Dist: pytest-cov; extra == "dev"
Requires-Dist: matplotlib; extra == "dev"
